mongorepository/__init__.py
mongorepository/models.py
mongorepository/repositories/async_mongo.py
mongorepository/repositories/base.py
mongorepository/repositories/mongo.py
mongorepository/utils/__init__.py
mongorepository/utils/decorators.py
mongorepository/utils/objects.py
mongorepository-0.7.1.dist-info/LICENSE
mongorepository-0.7.1.dist-info/METADATA
mongorepository-0.7.1.dist-info/WHEEL
mongorepository-0.7.1.dist-info/RECORD
