Metadata-Version: 2.1
Name: mongorepository
Version: 0.7.1
Summary: 
Author: Ramon Rodrigues
Author-email: ramon.srodrigues01@gmail.com
Requires-Python: >=3.9,<4.0
Classifier: Programming Language :: Python :: 3
Classifier: Programming Language :: Python :: 3.9
Classifier: Programming Language :: Python :: 3.10
Classifier: Programming Language :: Python :: 3.11
Requires-Dist: motor (>=3.1.1,<4.0.0)
Requires-Dist: polyfactory (>=2.21.0,<3.0.0)
Requires-Dist: pydantic (>=2.11.7,<3.0.0)
